pareidolia/__init__.py
pareidolia/__main__.py
pareidolia/detection.py
pareidolia/hic_utils.py
pareidolia/io.py
pareidolia/preprocess.py
pareidolia/stats.py
pareidolia/cli/__init__.py
pareidolia-1.2.0.dist-info/LICENSE
pareidolia-1.2.0.dist-info/METADATA
pareidolia-1.2.0.dist-info/WHEEL
pareidolia-1.2.0.dist-info/entry_points.txt
pareidolia-1.2.0.dist-info/top_level.txt
pareidolia-1.2.0.dist-info/RECORD
