Metadata-Version: 2.1
Name: pareidolia
Version: 1.2.0
Summary: Multi-sample change detection in Hi-C patterns
Home-page: https://github.com/cmdoret/pareidolia
Author: Cyril Matthey-Doret
Author-email: cyril.matthey-doret@pasteur.fr
License: MIT
Platform: UNKNOWN
Classifier: Development Status :: 4 - Beta
Classifier: Intended Audience :: Science/Research
Classifier: License :: OSI Approved :: MIT License
Classifier: Programming Language :: Python
Classifier: Programming Language :: Python :: 3
Classifier: Programming Language :: Python :: 3.6
Classifier: Programming Language :: Python :: 3.7
Classifier: Topic :: Scientific/Engineering
Classifier: Topic :: Scientific/Engineering :: Bio-Informatics
Classifier: Operating System :: OS Independent
Requires-Dist: chromosight
